setup.cfg
setup.py
Flask_Mage2Connector.egg-info/PKG-INFO
Flask_Mage2Connector.egg-info/SOURCES.txt
Flask_Mage2Connector.egg-info/dependency_links.txt
Flask_Mage2Connector.egg-info/not-zip-safe
Flask_Mage2Connector.egg-info/requires.txt
Flask_Mage2Connector.egg-info/top_level.txt
flask_mage2connector/__init__.py
flask_mage2connector/flask_mage2connector.py